sunburst/__init__.py
sunburst/cli.py
sunburst/pipeline.py
sunburst/modules/__init__.py
sunburst/modules/bend_bow.py
sunburst/modules/carry_tiger.py
sunburst/modules/grasp_tail.py
sunburst/modules/green_dragon.py
sunburst/utils/__init__.py
sunburst/utils/chisao.py
sunburst/utils/gpu.py
sunburst/utils/single_whip.py
sunburst_bayes-1.0.0.dist-info/METADATA
sunburst_bayes-1.0.0.dist-info/WHEEL
sunburst_bayes-1.0.0.dist-info/entry_points.txt
sunburst_bayes-1.0.0.dist-info/licenses/LICENSE
sunburst_bayes-1.0.0.dist-info/RECORD
