Metadata-Version: 2.4
Name: sunburst-bayes
Version: 1.0.0
Summary: GPU-accelerated Bayesian evidence calculation via radial shooting techniques
Project-URL: Homepage, https://github.com/sunburst-bayes/sunburst
Project-URL: Documentation, https://github.com/sunburst-bayes/sunburst#readme
Project-URL: Repository, https://github.com/sunburst-bayes/sunburst
Project-URL: Issues, https://github.com/sunburst-bayes/sunburst/issues
Author-email: Ira Wolfson <wolfsoni@braude.ac.il>
License-Expression: MIT
License-File: LICENSE
Keywords: bayesian,bayesian-inference,cosmology,evidence,gpu,mcmc,nested-sampling,parameter-estimation
Classifier: Development Status :: 5 - Production/Stable
Classifier: Intended Audience :: Science/Research
Classifier: License :: OSI Approved :: MIT License
Classifier: Operating System :: OS Independent
Classifier: Programming Language :: Python :: 3
Classifier: Programming Language :: Python :: 3.9
Classifier: Programming Language :: Python :: 3.10
Classifier: Programming Language :: Python :: 3.11
Classifier: Programming Language :: Python :: 3.12
Classifier: Topic :: Scientific/Engineering
Classifier: Topic :: Scientific/Engineering :: Astronomy
Classifier: Topic :: Scientific/Engineering :: Physics
Requires-Python: >=3.9
Requires-Dist: numpy>=1.20
Requires-Dist: scipy>=1.7
Provides-Extra: dev
Requires-Dist: black>=23.0; extra == 'dev'
Requires-Dist: pytest-cov>=4.0; extra == 'dev'
Requires-Dist: pytest>=7.0; extra == 'dev'
Requires-Dist: ruff>=0.1; extra == 'dev'
